{
  "0.05": {
    "1.00": {
      "b": 1.0,
      "H_star": 0.05,
      "f_BM": 0.7740179509699184,
      "A_BM": 0.579059700784851,
      "G_BM": 0.4482026030907445,
      "BM_count": 0,
      "R_min": 0.6,
      "Rmax_global": 20.045780284087446
    },
    "2.00": {
      "b": 2.0,
      "H_star": 0.05,
      "f_BM": 0.7119056917244589,
      "A_BM": 0.6543867259487172,
      "G_BM": 0.4658616347918254,
      "BM_count": 0,
      "R_min": 0.6,
      "Rmax_global": 20.045780284087446
    },
    "3.00": {
      "b": 3.0,
      "H_star": 0.05,
      "f_BM": 0.651717787554463,
      "A_BM": 0.721416224090579,
      "G_BM": 0.47015978547020687,
      "BM_count": 0,
      "R_min": 0.6,
      "Rmax_global": 20.045780284087446
    },
    "4.00": {
      "b": 4.0,
      "H_star": 0.05,
      "f_BM": 0.5960037507617683,
      "A_BM": 0.779352090901498,
      "G_BM": 0.4644967693413194,
      "BM_count": 0,
      "R_min": 0.6,
      "Rmax_global": 20.045780284087446
    },
    "5.00": {
      "b": 5.0,
      "H_star": 0.05,
      "f_BM": 0.5455113530559283,
      "A_BM": 0.8291065023735599,
      "G_BM": 0.4522870099372689,
      "BM_count": 0,
      "R_min": 0.6,
      "Rmax_global": 20.045780284087446
    },
    "6.00": {
      "b": 6.0,
      "H_star": 0.05,
      "f_BM": 0.5001020667494593,
      "A_BM": 0.8720415727762872,
      "G_BM": 0.4361097928368703,
      "BM_count": 0,
      "R_min": 0.6,
      "Rmax_global": 20.045780284087446
    },
    "8.00": {
      "b": 8.0,
      "H_star": 0.05,
      "f_BM": 0.4226077452076759,
      "A_BM": 0.9423400816747826,
      "G_BM": 0.39824021713539703,
      "BM_count": 0,
      "R_min": 0.6,
      "Rmax_global": 20.045780284087446
    },
    "10.00": {
      "b": 10.0,
      "H_star": 0.05,
      "f_BM": 0.3595145942202531,
      "A_BM": 0.9978019369607029,
      "G_BM": 0.3587243584786097,
      "BM_count": 0,
      "R_min": 0.6,
      "Rmax_global": 20.045780284087446
    },
    "12.00": {
      "b": 12.0,
      "H_star": 0.05,
      "f_BM": 0.3075306242736532,
      "A_BM": 1.0430731308575916,
      "G_BM": 0.3207769310957091,
      "BM_count": 0,
      "R_min": 0.6,
      "Rmax_global": 20.045780284087446
    },
    "16.00": {
      "b": 16.0,
      "H_star": 0.05,
      "f_BM": 0.2278709530662415,
      "A_BM": 1.1134968027549363,
      "G_BM": 0.25373357767998006,
      "BM_count": 0,
      "R_min": 0.6,
      "Rmax_global": 20.045780284087446
    },
    "20.00": {
      "b": 20.0,
      "H_star": 0.05,
      "f_BM": 0.1709144918473771,
      "A_BM": 1.1666337959710948,
      "G_BM": 0.19939462241037628,
      "BM_count": 0,
      "R_min": 0.6,
      "Rmax_global": 20.045780284087446
    },
    "25.00": {
      "b": 25.0,
      "H_star": 0.05,
      "f_BM": 0.12072747395446205,
      "A_BM": 1.2179712089621262,
      "G_BM": 0.14704258740725976,
      "BM_count": 0,
      "R_min": 0.6,
      "Rmax_global": 20.045780284087446
    },
    "32.00": {
      "b": 32.0,
      "H_star": 0.05,
      "f_BM": 0.07535084621648651,
      "A_BM": 1.2721885594731253,
      "G_BM": 0.09586048450323296,
      "BM_count": 0,
      "R_min": 0.6,
      "Rmax_global": 20.045780284087446
    },
    "40.00": {
      "b": 40.0,
      "H_star": 0.05,
      "f_BM": 0.04462308910383492,
      "A_BM": 1.3184831592759392,
      "G_BM": 0.058834791498276,
      "BM_count": 0,
      "R_min": 0.6,
      "Rmax_global": 20.045780284087446
    }
  },
  "0.10": {
    "1.00": {
      "b": 1.0,
      "H_star": 0.1,
      "f_BM": 0.5968659133682493,
      "A_BM": 0.8006153725874795,
      "G_BM": 0.4778600256160872,
      "BM_count": 0,
      "R_min": 0.6,
      "Rmax_global": 20.045780284087446
    },
    "2.00": {
      "b": 2.0,
      "H_star": 0.1,
      "f_BM": 0.5067853426851939,
      "A_BM": 0.8773003304952822,
      "G_BM": 0.44460294862788546,
      "BM_count": 0,
      "R_min": 0.6,
      "Rmax_global": 20.045780284087446
    },
    "3.00": {
      "b": 3.0,
      "H_star": 0.1,
      "f_BM": 0.42638067215284875,
      "A_BM": 0.9438980404171377,
      "G_BM": 0.40245988091681595,
      "BM_count": 0,
      "R_min": 0.6,
      "Rmax_global": 20.045780284087446
    },
    "4.00": {
      "b": 4.0,
      "H_star": 0.1,
      "f_BM": 0.3579892774437384,
      "A_BM": 1.0001624299366199,
      "G_BM": 0.35804742561938413,
      "BM_count": 0,
      "R_min": 0.6,
      "Rmax_global": 20.045780284087446
    },
    "5.00": {
      "b": 5.0,
      "H_star": 0.1,
      "f_BM": 0.30105028521906435,
      "A_BM": 1.0474520630453525,
      "G_BM": 0.31533574233310074,
      "BM_count": 0,
      "R_min": 0.6,
      "Rmax_global": 20.045780284087446
    },
    "6.00": {
      "b": 6.0,
      "H_star": 0.1,
      "f_BM": 0.25396499387127763,
      "A_BM": 1.087444734476528,
      "G_BM": 0.27617289532668454,
      "BM_count": 0,
      "R_min": 0.6,
      "Rmax_global": 20.045780284087446
    },
    "8.00": {
      "b": 8.0,
      "H_star": 0.1,
      "f_BM": 0.1826873494240258,
      "A_BM": 1.1511894686887907,
      "G_BM": 0.21030775271960772,
      "BM_count": 0,
      "R_min": 0.6,
      "Rmax_global": 20.045780284087446
    },
    "10.00": {
      "b": 10.0,
      "H_star": 0.1,
      "f_BM": 0.1331641719286213,
      "A_BM": 1.199883585642161,
      "G_BM": 0.15978150409278333,
      "BM_count": 0,
      "R_min": 0.6,
      "Rmax_global": 20.045780284087446
    },
    "12.00": {
      "b": 12.0,
      "H_star": 0.1,
      "f_BM": 0.09813515944716159,
      "A_BM": 1.238551518936605,
      "G_BM": 0.1215454507943679,
      "BM_count": 0,
      "R_min": 0.6,
      "Rmax_global": 20.045780284087446
    },
    "16.00": {
      "b": 16.0,
      "H_star": 0.1,
      "f_BM": 0.054648384076352495,
      "A_BM": 1.296738266213401,
      "G_BM": 0.07086465081853337,
      "BM_count": 0,
      "R_min": 0.6,
      "Rmax_global": 20.045780284087446
    },
    "20.00": {
      "b": 20.0,
      "H_star": 0.1,
      "f_BM": 0.031181437632086705,
      "A_BM": 1.339046489250214,
      "G_BM": 0.04175339459102021,
      "BM_count": 0,
      "R_min": 0.6,
      "Rmax_global": 20.045780284087446
    },
    "25.00": {
      "b": 25.0,
      "H_star": 0.1,
      "f_BM": 0.015835176807356986,
      "A_BM": 1.3786148683347639,
      "G_BM": 0.021830610189332158,
      "BM_count": 0,
      "R_min": 0.6,
      "Rmax_global": 20.045780284087446
    },
    "32.00": {
      "b": 32.0,
      "H_star": 0.1,
      "f_BM": 0.006323228061921845,
      "A_BM": 1.41900947240648,
      "G_BM": 0.008972720516053564,
      "BM_count": 0,
      "R_min": 0.6,
      "Rmax_global": 20.045780284087446
    },
    "40.00": {
      "b": 40.0,
      "H_star": 0.1,
      "f_BM": 0.002281325889699684,
      "A_BM": 1.4523691484483778,
      "G_BM": 0.003313327339756368,
      "BM_count": 0,
      "R_min": 0.6,
      "Rmax_global": 20.045780284087446
    }
  },
  "0.20": {
    "1.00": {
      "b": 1.0,
      "H_star": 0.2,
      "f_BM": 0.3501749651946442,
      "A_BM": 1.0426421730294468,
      "G_BM": 0.36510718665105474,
      "BM_count": 0,
      "R_min": 0.6,
      "Rmax_global": 20.045780284087446
    },
    "2.00": {
      "b": 2.0,
      "H_star": 0.2,
      "f_BM": 0.256138654088371,
      "A_BM": 1.1056435117906254,
      "G_BM": 0.28319804101159074,
      "BM_count": 0,
      "R_min": 0.6,
      "Rmax_global": 20.045780284087446
    },
    "3.00": {
      "b": 3.0,
      "H_star": 0.2,
      "f_BM": 0.18413195321763703,
      "A_BM": 1.1597726648687654,
      "G_BM": 0.21355120607070974,
      "BM_count": 0,
      "R_min": 0.6,
      "Rmax_global": 20.045780284087446
    },
    "4.00": {
      "b": 4.0,
      "H_star": 0.2,
      "f_BM": 0.13182576097651408,
      "A_BM": 1.205032070515717,
      "G_BM": 0.15885426969683875,
      "BM_count": 0,
      "R_min": 0.6,
      "Rmax_global": 20.045780284087446
    },
    "5.00": {
      "b": 5.0,
      "H_star": 0.2,
      "f_BM": 0.09465713865360233,
      "A_BM": 1.2426609753385531,
      "G_BM": 0.11762673224204213,
      "BM_count": 0,
      "R_min": 0.6,
      "Rmax_global": 20.045780284087446
    },
    "6.00": {
      "b": 6.0,
      "H_star": 0.2,
      "f_BM": 0.06837742530096358,
      "A_BM": 1.2741246753098066,
      "G_BM": 0.08712136481011078,
      "BM_count": 0,
      "R_min": 0.6,
      "Rmax_global": 20.045780284087446
    },
    "8.00": {
      "b": 8.0,
      "H_star": 0.2,
      "f_BM": 0.03643150042222886,
      "A_BM": 1.323448388125246,
      "G_BM": 0.048215210510783,
      "BM_count": 0,
      "R_min": 0.6,
      "Rmax_global": 20.045780284087446
    },
    "10.00": {
      "b": 10.0,
      "H_star": 0.2,
      "f_BM": 0.019920558493682888,
      "A_BM": 1.3603206605790534,
      "G_BM": 0.027098347289230378,
      "BM_count": 0,
      "R_min": 0.6,
      "Rmax_global": 20.045780284087446
    },
    "12.00": {
      "b": 12.0,
      "H_star": 0.2,
      "f_BM": 0.011130801387700428,
      "A_BM": 1.3890385642088072,
      "G_BM": 0.0154611123780648,
      "BM_count": 0,
      "R_min": 0.6,
      "Rmax_global": 20.045780284087446
    },
    "16.00": {
      "b": 16.0,
      "H_star": 0.2,
      "f_BM": 0.003652488032418222,
      "A_BM": 1.4312375664602814,
      "G_BM": 0.005227578083043557,
      "BM_count": 0,
      "R_min": 0.6,
      "Rmax_global": 20.045780284087446
    },
    "20.00": {
      "b": 20.0,
      "H_star": 0.2,
      "f_BM": 0.0012581284697533368,
      "A_BM": 1.4611145705312474,
      "G_BM": 0.0018382698387567821,
      "BM_count": 0,
      "R_min": 0.6,
      "Rmax_global": 20.045780284087446
    },
    "25.00": {
      "b": 25.0,
      "H_star": 0.2,
      "f_BM": 0.0003481819254239712,
      "A_BM": 1.4884249569953683,
      "G_BM": 0.0005182426673757389,
      "BM_count": 0,
      "R_min": 0.6,
      "Rmax_global": 20.045780284087446
    },
    "32.00": {
      "b": 32.0,
      "H_star": 0.2,
      "f_BM": 6.128688085314171e-05,
      "A_BM": 1.5156678461575654,
      "G_BM": 9.289055470039663e-05,
      "BM_count": 0,
      "R_min": 0.6,
      "Rmax_global": 20.045780284087446
    },
    "40.00": {
      "b": 40.0,
      "H_star": 0.2,
      "f_BM": 8.933377181420661e-06,
      "A_BM": 1.5376793148386323,
      "G_BM": 1.3736669303521995e-05,
      "BM_count": 0,
      "R_min": 0.6,
      "Rmax_global": 20.045780284087446
    }
  },
  "0.50": {
    "1.00": {
      "b": 1.0,
      "H_star": 0.5,
      "f_BM": 0.060222871223518624,
      "A_BM": 1.3536863262243242,
      "G_BM": 0.0815228773012455,
      "BM_count": 0,
      "R_min": 0.6,
      "Rmax_global": 20.045780284087446
    },
    "2.00": {
      "b": 2.0,
      "H_star": 0.5,
      "f_BM": 0.030505337959162684,
      "A_BM": 1.3804601922870654,
      "G_BM": 0.04211140470488763,
      "BM_count": 0,
      "R_min": 0.6,
      "Rmax_global": 20.045780284087446
    },
    "3.00": {
      "b": 3.0,
      "H_star": 0.5,
      "f_BM": 0.014909900971413611,
      "A_BM": 1.40435026693399,
      "G_BM": 0.020938723409164063,
      "BM_count": 0,
      "R_min": 0.6,
      "Rmax_global": 20.045780284087446
    },
    "4.00": {
      "b": 4.0,
      "H_star": 0.5,
      "f_BM": 0.007226441217218002,
      "A_BM": 1.4249876392867533,
      "G_BM": 0.010297589410567973,
      "BM_count": 0,
      "R_min": 0.6,
      "Rmax_global": 20.045780284087446
    },
    "5.00": {
      "b": 5.0,
      "H_star": 0.5,
      "f_BM": 0.003526255917167614,
      "A_BM": 1.4426073235130057,
      "G_BM": 0.0050870026106870705,
      "BM_count": 0,
      "R_min": 0.6,
      "Rmax_global": 20.045780284087446
    },
    "6.00": {
      "b": 6.0,
      "H_star": 0.5,
      "f_BM": 0.0017444322420549683,
      "A_BM": 1.4576477458798553,
      "G_BM": 0.0025427677254715665,
      "BM_count": 0,
      "R_min": 0.6,
      "Rmax_global": 20.045780284087446
    },
    "8.00": {
      "b": 8.0,
      "H_star": 0.5,
      "f_BM": 0.0004481121781520349,
      "A_BM": 1.4817363614535344,
      "G_BM": 0.0006639841083780142,
      "BM_count": 0,
      "R_min": 0.6,
      "Rmax_global": 20.045780284087446
    },
    "10.00": {
      "b": 10.0,
      "H_star": 0.5,
      "f_BM": 0.0001224238866433235,
      "A_BM": 1.500091897451316,
      "G_BM": 0.00018364708040814794,
      "BM_count": 0,
      "R_min": 0.6,
      "Rmax_global": 20.045780284087446
    },
    "12.00": {
      "b": 12.0,
      "H_star": 0.5,
      "f_BM": 3.5244883391238046e-05,
      "A_BM": 1.5145581170362088,
      "G_BM": 5.3380424224194246e-05,
      "BM_count": 0,
      "R_min": 0.6,
      "Rmax_global": 20.045780284087446
    },
    "16.00": {
      "b": 16.0,
      "H_star": 0.5,
      "f_BM": 3.301261648483394e-06,
      "A_BM": 1.5360411581384021,
      "G_BM": 5.070873765854323e-06,
      "BM_count": 0,
      "R_min": 0.6,
      "Rmax_global": 20.045780284087446
    },
    "20.00": {
      "b": 20.0,
      "H_star": 0.5,
      "f_BM": 3.4891729530386615e-07,
      "A_BM": 1.5514020730203877,
      "G_BM": 5.413110152470847e-07,
      "BM_count": 0,
      "R_min": 0.6,
      "Rmax_global": 20.045780284087446
    },
    "25.00": {
      "b": 25.0,
      "H_star": 0.5,
      "f_BM": 2.3699586246386625e-08,
      "A_BM": 1.5655628860906932,
      "G_BM": 3.710319264304834e-08,
      "BM_count": 0,
      "R_min": 0.6,
      "Rmax_global": 20.045780284087446
    },
    "32.00": {
      "b": 32.0,
      "H_star": 0.5,
      "f_BM": 6.413745167137394e-10,
      "A_BM": 1.5798340285086705,
      "G_BM": 1.0132652865226686e-09,
      "BM_count": 0,
      "R_min": 0.6,
      "Rmax_global": 20.045780284087446
    },
    "40.00": {
      "b": 40.0,
      "H_star": 0.5,
      "f_BM": 1.2063776421555973e-11,
      "A_BM": 1.5915089486391096,
      "G_BM": 1.9199608129287828e-11,
      "BM_count": 0,
      "R_min": 0.6,
      "Rmax_global": 20.045780284087446
    }
  },
  "1.00": {
    "1.00": {
      "b": 1.0,
      "H_star": 1.0,
      "f_BM": 0.0009301849818134848,
      "A_BM": 1.561131454833147,
      "G_BM": 0.0014521410339224299,
      "BM_count": 0,
      "R_min": 0.6,
      "Rmax_global": 20.045780284087446
    },
    "2.00": {
      "b": 2.0,
      "H_star": 1.0,
      "f_BM": 0.00030625505606184046,
      "A_BM": 1.5674908362269124,
      "G_BM": 0.00048005199392509425,
      "BM_count": 0,
      "R_min": 0.6,
      "Rmax_global": 20.045780284087446
    },
    "3.00": {
      "b": 3.0,
      "H_star": 1.0,
      "f_BM": 9.481616789171752e-05,
      "A_BM": 1.573962958007818,
      "G_BM": 0.0001492371360818136,
      "BM_count": 0,
      "R_min": 0.6,
      "Rmax_global": 20.045780284087446
    },
    "4.00": {
      "b": 4.0,
      "H_star": 1.0,
      "f_BM": 2.8901824996104238e-05,
      "A_BM": 1.5801352179702075,
      "G_BM": 4.566879153995596e-05,
      "BM_count": 0,
      "R_min": 0.6,
      "Rmax_global": 20.045780284087446
    },
    "5.00": {
      "b": 5.0,
      "H_star": 1.0,
      "f_BM": 8.901769032902282e-06,
      "A_BM": 1.5858573142849002,
      "G_BM": 1.4116935530902907e-05,
      "BM_count": 0,
      "R_min": 0.6,
      "Rmax_global": 20.045780284087446
    },
    "6.00": {
      "b": 6.0,
      "H_star": 1.0,
      "f_BM": 2.8049029318490728e-06,
      "A_BM": 1.5911069679686427,
      "G_BM": 4.4629005993407345e-06,
      "BM_count": 0,
      "R_min": 0.6,
      "Rmax_global": 20.045780284087446
    },
    "8.00": {
      "b": 8.0,
      "H_star": 1.0,
      "f_BM": 3.0261264921773105e-07,
      "A_BM": 1.6003435753369022,
      "G_BM": 4.842842089912755e-07,
      "BM_count": 0,
      "R_min": 0.6,
      "Rmax_global": 20.045780284087446
    },
    "10.00": {
      "b": 10.0,
      "H_star": 1.0,
      "f_BM": 3.633697833594649e-08,
      "A_BM": 1.6082699018097333,
      "G_BM": 5.843966858041507e-08,
      "BM_count": 0,
      "R_min": 0.6,
      "Rmax_global": 20.045780284087446
    },
    "12.00": {
      "b": 12.0,
      "H_star": 1.0,
      "f_BM": 4.776048353627121e-09,
      "A_BM": 1.615298056023061,
      "G_BM": 7.71474162108603e-09,
      "BM_count": 0,
      "R_min": 0.6,
      "Rmax_global": 20.045780284087446
    },
    "16.00": {
      "b": 16.0,
      "H_star": 1.0,
      "f_BM": 1.0041205211528513e-10,
      "A_BM": 1.627846935010961,
      "G_BM": 1.6345545127402779e-10,
      "BM_count": 0,
      "R_min": 0.6,
      "Rmax_global": 20.045780284087446
    },
    "20.00": {
      "b": 20.0,
      "H_star": 1.0,
      "f_BM": 2.421561545667997e-12,
      "A_BM": 1.6394958063847507,
      "G_BM": 3.970139999025256e-12,
      "BM_count": 0,
      "R_min": 0.6,
      "Rmax_global": 20.045780284087446
    },
    "25.00": {
      "b": 25.0,
      "H_star": 1.0,
      "f_BM": 2.0246290094982767e-14,
      "A_BM": 1.6528122507197518,
      "G_BM": 3.3463316300613484e-14,
      "BM_count": 0,
      "R_min": 0.6,
      "Rmax_global": 20.045780284087446
    },
    "32.00": {
      "b": 32.0,
      "H_star": 1.0,
      "f_BM": 1.420579183610467e-18,
      "A_BM": 1.6621674972110598,
      "G_BM": 2.3612405462119407e-18,
      "BM_count": 0,
      "R_min": 0.6,
      "Rmax_global": 20.045780284087446
    },
    "40.00": {
      "b": 40.0,
      "H_star": 1.0,
      "f_BM": 0.0,
      "A_BM": 0.0,
      "G_BM": 0.0,
      "BM_count": 0,
      "R_min": 0.6,
      "Rmax_global": 20.045780284087446
    }
  },
  "1.50": {
    "1.00": {
      "b": 1.0,
      "H_star": 1.5,
      "f_BM": 2.8958571692969556e-09,
      "A_BM": 1.6588287047702808,
      "G_BM": 4.8037309973446e-09,
      "BM_count": 0,
      "R_min": 0.6,
      "Rmax_global": 20.045780284087446
    },
    "2.00": {
      "b": 2.0,
      "H_star": 1.5,
      "f_BM": 0.0,
      "A_BM": 0.0,
      "G_BM": 0.0,
      "BM_count": 0,
      "R_min": 0.6,
      "Rmax_global": 20.045780284087446
    },
    "3.00": {
      "b": 3.0,
      "H_star": 1.5,
      "f_BM": 0.0,
      "A_BM": 0.0,
      "G_BM": 0.0,
      "BM_count": 0,
      "R_min": 0.6,
      "Rmax_global": 20.045780284087446
    },
    "4.00": {
      "b": 4.0,
      "H_star": 1.5,
      "f_BM": 0.0,
      "A_BM": 0.0,
      "G_BM": 0.0,
      "BM_count": 0,
      "R_min": 0.6,
      "Rmax_global": 20.045780284087446
    },
    "5.00": {
      "b": 5.0,
      "H_star": 1.5,
      "f_BM": 0.0,
      "A_BM": 0.0,
      "G_BM": 0.0,
      "BM_count": 0,
      "R_min": 0.6,
      "Rmax_global": 20.045780284087446
    },
    "6.00": {
      "b": 6.0,
      "H_star": 1.5,
      "f_BM": 0.0,
      "A_BM": 0.0,
      "G_BM": 0.0,
      "BM_count": 0,
      "R_min": 0.6,
      "Rmax_global": 20.045780284087446
    },
    "8.00": {
      "b": 8.0,
      "H_star": 1.5,
      "f_BM": 0.0,
      "A_BM": 0.0,
      "G_BM": 0.0,
      "BM_count": 0,
      "R_min": 0.6,
      "Rmax_global": 20.045780284087446
    },
    "10.00": {
      "b": 10.0,
      "H_star": 1.5,
      "f_BM": 0.0,
      "A_BM": 0.0,
      "G_BM": 0.0,
      "BM_count": 0,
      "R_min": 0.6,
      "Rmax_global": 20.045780284087446
    },
    "12.00": {
      "b": 12.0,
      "H_star": 1.5,
      "f_BM": 0.0,
      "A_BM": 0.0,
      "G_BM": 0.0,
      "BM_count": 0,
      "R_min": 0.6,
      "Rmax_global": 20.045780284087446
    },
    "16.00": {
      "b": 16.0,
      "H_star": 1.5,
      "f_BM": 0.0,
      "A_BM": 0.0,
      "G_BM": 0.0,
      "BM_count": 0,
      "R_min": 0.6,
      "Rmax_global": 20.045780284087446
    },
    "20.00": {
      "b": 20.0,
      "H_star": 1.5,
      "f_BM": 0.0,
      "A_BM": 0.0,
      "G_BM": 0.0,
      "BM_count": 0,
      "R_min": 0.6,
      "Rmax_global": 20.045780284087446
    },
    "25.00": {
      "b": 25.0,
      "H_star": 1.5,
      "f_BM": 0.0,
      "A_BM": 0.0,
      "G_BM": 0.0,
      "BM_count": 0,
      "R_min": 0.6,
      "Rmax_global": 20.045780284087446
    },
    "32.00": {
      "b": 32.0,
      "H_star": 1.5,
      "f_BM": 0.0,
      "A_BM": 0.0,
      "G_BM": 0.0,
      "BM_count": 0,
      "R_min": 0.6,
      "Rmax_global": 20.045780284087446
    },
    "40.00": {
      "b": 40.0,
      "H_star": 1.5,
      "f_BM": 0.0,
      "A_BM": 0.0,
      "G_BM": 0.0,
      "BM_count": 0,
      "R_min": 0.6,
      "Rmax_global": 20.045780284087446
    }
  },
  "2.00": {
    "1.00": {
      "b": 1.0,
      "H_star": 2.0,
      "f_BM": 0.0,
      "A_BM": 0.0,
      "G_BM": 0.0,
      "BM_count": 0,
      "R_min": 0.6,
      "Rmax_global": 20.045780284087446
    },
    "2.00": {
      "b": 2.0,
      "H_star": 2.0,
      "f_BM": 0.0,
      "A_BM": 0.0,
      "G_BM": 0.0,
      "BM_count": 0,
      "R_min": 0.6,
      "Rmax_global": 20.045780284087446
    },
    "3.00": {
      "b": 3.0,
      "H_star": 2.0,
      "f_BM": 0.0,
      "A_BM": 0.0,
      "G_BM": 0.0,
      "BM_count": 0,
      "R_min": 0.6,
      "Rmax_global": 20.045780284087446
    },
    "4.00": {
      "b": 4.0,
      "H_star": 2.0,
      "f_BM": 0.0,
      "A_BM": 0.0,
      "G_BM": 0.0,
      "BM_count": 0,
      "R_min": 0.6,
      "Rmax_global": 20.045780284087446
    },
    "5.00": {
      "b": 5.0,
      "H_star": 2.0,
      "f_BM": 0.0,
      "A_BM": 0.0,
      "G_BM": 0.0,
      "BM_count": 0,
      "R_min": 0.6,
      "Rmax_global": 20.045780284087446
    },
    "6.00": {
      "b": 6.0,
      "H_star": 2.0,
      "f_BM": 0.0,
      "A_BM": 0.0,
      "G_BM": 0.0,
      "BM_count": 0,
      "R_min": 0.6,
      "Rmax_global": 20.045780284087446
    },
    "8.00": {
      "b": 8.0,
      "H_star": 2.0,
      "f_BM": 0.0,
      "A_BM": 0.0,
      "G_BM": 0.0,
      "BM_count": 0,
      "R_min": 0.6,
      "Rmax_global": 20.045780284087446
    },
    "10.00": {
      "b": 10.0,
      "H_star": 2.0,
      "f_BM": 0.0,
      "A_BM": 0.0,
      "G_BM": 0.0,
      "BM_count": 0,
      "R_min": 0.6,
      "Rmax_global": 20.045780284087446
    },
    "12.00": {
      "b": 12.0,
      "H_star": 2.0,
      "f_BM": 0.0,
      "A_BM": 0.0,
      "G_BM": 0.0,
      "BM_count": 0,
      "R_min": 0.6,
      "Rmax_global": 20.045780284087446
    },
    "16.00": {
      "b": 16.0,
      "H_star": 2.0,
      "f_BM": 0.0,
      "A_BM": 0.0,
      "G_BM": 0.0,
      "BM_count": 0,
      "R_min": 0.6,
      "Rmax_global": 20.045780284087446
    },
    "20.00": {
      "b": 20.0,
      "H_star": 2.0,
      "f_BM": 0.0,
      "A_BM": 0.0,
      "G_BM": 0.0,
      "BM_count": 0,
      "R_min": 0.6,
      "Rmax_global": 20.045780284087446
    },
    "25.00": {
      "b": 25.0,
      "H_star": 2.0,
      "f_BM": 0.0,
      "A_BM": 0.0,
      "G_BM": 0.0,
      "BM_count": 0,
      "R_min": 0.6,
      "Rmax_global": 20.045780284087446
    },
    "32.00": {
      "b": 32.0,
      "H_star": 2.0,
      "f_BM": 0.0,
      "A_BM": 0.0,
      "G_BM": 0.0,
      "BM_count": 0,
      "R_min": 0.6,
      "Rmax_global": 20.045780284087446
    },
    "40.00": {
      "b": 40.0,
      "H_star": 2.0,
      "f_BM": 0.0,
      "A_BM": 0.0,
      "G_BM": 0.0,
      "BM_count": 0,
      "R_min": 0.6,
      "Rmax_global": 20.045780284087446
    }
  }
}