{
  "0.05": {
    "1.00": {
      "b": 1.0,
      "H_star": 0.05,
      "f_BM": 0.8352428230071101,
      "A_BM": 0.682169235214972,
      "G_BM": 0.5697769577895545,
      "BM_count": 0,
      "R_min": 0.425,
      "Rmax_global": 20.045780284087446
    },
    "2.00": {
      "b": 2.0,
      "H_star": 0.05,
      "f_BM": 0.7871604393830092,
      "A_BM": 0.7818205252852216,
      "G_BM": 0.6154181882021701,
      "BM_count": 0,
      "R_min": 0.425,
      "Rmax_global": 20.045780284087446
    },
    "3.00": {
      "b": 3.0,
      "H_star": 0.05,
      "f_BM": 0.7393869566459128,
      "A_BM": 0.8717094442002761,
      "G_BM": 0.6445305930267423,
      "BM_count": 0,
      "R_min": 0.425,
      "Rmax_global": 20.045780284087446
    },
    "4.00": {
      "b": 4.0,
      "H_star": 0.05,
      "f_BM": 0.6940103895417988,
      "A_BM": 0.9503956693279602,
      "G_BM": 0.6595844686891362,
      "BM_count": 0,
      "R_min": 0.425,
      "Rmax_global": 20.045780284087446
    },
    "5.00": {
      "b": 5.0,
      "H_star": 0.05,
      "f_BM": 0.6518108417944312,
      "A_BM": 1.0187719396998027,
      "G_BM": 0.6640465956122739,
      "BM_count": 0,
      "R_min": 0.425,
      "Rmax_global": 20.045780284087446
    },
    "6.00": {
      "b": 6.0,
      "H_star": 0.05,
      "f_BM": 0.6128773373235448,
      "A_BM": 1.0784200943272981,
      "G_BM": 0.6609392359275205,
      "BM_count": 0,
      "R_min": 0.425,
      "Rmax_global": 20.045780284087446
    },
    "8.00": {
      "b": 8.0,
      "H_star": 0.05,
      "f_BM": 0.5439429056728222,
      "A_BM": 1.1774846402429393,
      "G_BM": 0.6404844165988621,
      "BM_count": 0,
      "R_min": 0.425,
      "Rmax_global": 20.045780284087446
    },
    "10.00": {
      "b": 10.0,
      "H_star": 0.05,
      "f_BM": 0.4850444339637359,
      "A_BM": 1.2569739489769345,
      "G_BM": 0.6096882175886791,
      "BM_count": 0,
      "R_min": 0.425,
      "Rmax_global": 20.045780284087446
    },
    "12.00": {
      "b": 12.0,
      "H_star": 0.05,
      "f_BM": 0.4342076694683682,
      "A_BM": 1.3227980799197134,
      "G_BM": 0.574369071459171,
      "BM_count": 0,
      "R_min": 0.425,
      "Rmax_global": 20.045780284087446
    },
    "16.00": {
      "b": 16.0,
      "H_star": 0.05,
      "f_BM": 0.3510553230206172,
      "A_BM": 1.426999558174864,
      "G_BM": 0.5009557908453549,
      "BM_count": 0,
      "R_min": 0.425,
      "Rmax_global": 20.045780284087446
    },
    "20.00": {
      "b": 20.0,
      "H_star": 0.05,
      "f_BM": 0.2862726245868805,
      "A_BM": 1.5071864124657863,
      "G_BM": 0.4314662100382653,
      "BM_count": 0,
      "R_min": 0.425,
      "Rmax_global": 20.045780284087446
    },
    "25.00": {
      "b": 25.0,
      "H_star": 0.05,
      "f_BM": 0.22370351778274913,
      "A_BM": 1.586034578492534,
      "G_BM": 0.3548015145338596,
      "BM_count": 0,
      "R_min": 0.425,
      "Rmax_global": 20.045780284087446
    },
    "32.00": {
      "b": 32.0,
      "H_star": 0.05,
      "f_BM": 0.16010330133365686,
      "A_BM": 1.670885185181334,
      "G_BM": 0.26751423429703014,
      "BM_count": 0,
      "R_min": 0.425,
      "Rmax_global": 20.045780284087446
    },
    "40.00": {
      "b": 40.0,
      "H_star": 0.05,
      "f_BM": 0.11038379486082626,
      "A_BM": 1.7447213426800037,
      "G_BM": 0.1925889627796949,
      "BM_count": 0,
      "R_min": 0.425,
      "Rmax_global": 20.045780284087446
    }
  },
  "0.10": {
    "1.00": {
      "b": 1.0,
      "H_star": 0.1,
      "f_BM": 0.6963821368835595,
      "A_BM": 0.970567343332042,
      "G_BM": 0.6758857605389668,
      "BM_count": 0,
      "R_min": 0.425,
      "Rmax_global": 20.045780284087446
    },
    "2.00": {
      "b": 2.0,
      "H_star": 0.1,
      "f_BM": 0.6196594434517785,
      "A_BM": 1.0805403987556936,
      "G_BM": 0.6695670621201159,
      "BM_count": 0,
      "R_min": 0.425,
      "Rmax_global": 20.045780284087446
    },
    "3.00": {
      "b": 3.0,
      "H_star": 0.1,
      "f_BM": 0.5477982977105372,
      "A_BM": 1.1771387932991118,
      "G_BM": 0.6448346271382893,
      "BM_count": 0,
      "R_min": 0.425,
      "Rmax_global": 20.045780284087446
    },
    "4.00": {
      "b": 4.0,
      "H_star": 0.1,
      "f_BM": 0.4835655566774384,
      "A_BM": 1.2596244802453567,
      "G_BM": 0.6091110129943749,
      "BM_count": 0,
      "R_min": 0.425,
      "Rmax_global": 20.045780284087446
    },
    "5.00": {
      "b": 5.0,
      "H_star": 0.1,
      "f_BM": 0.42736051372170686,
      "A_BM": 1.32966174330129,
      "G_BM": 0.5682449256933396,
      "BM_count": 0,
      "R_min": 0.425,
      "Rmax_global": 20.045780284087446
    },
    "6.00": {
      "b": 6.0,
      "H_star": 0.1,
      "f_BM": 0.37853767936864696,
      "A_BM": 1.389464324164114,
      "G_BM": 0.5259646008346092,
      "BM_count": 0,
      "R_min": 0.425,
      "Rmax_global": 20.045780284087446
    },
    "8.00": {
      "b": 8.0,
      "H_star": 0.1,
      "f_BM": 0.2992636164698999,
      "A_BM": 1.486023266401306,
      "G_BM": 0.4447126968616683,
      "BM_count": 0,
      "R_min": 0.425,
      "Rmax_global": 20.045780284087446
    },
    "10.00": {
      "b": 10.0,
      "H_star": 0.1,
      "f_BM": 0.23881812002616806,
      "A_BM": 1.560944246461549,
      "G_BM": 0.37278177040561067,
      "BM_count": 0,
      "R_min": 0.425,
      "Rmax_global": 20.045780284087446
    },
    "12.00": {
      "b": 12.0,
      "H_star": 0.1,
      "f_BM": 0.1920626264573103,
      "A_BM": 1.6212380847219099,
      "G_BM": 0.31137924466430933,
      "BM_count": 0,
      "R_min": 0.425,
      "Rmax_global": 20.045780284087446
    },
    "16.00": {
      "b": 16.0,
      "H_star": 0.1,
      "f_BM": 0.1264357229948714,
      "A_BM": 1.7134374258871665,
      "G_BM": 0.2166396997485153,
      "BM_count": 0,
      "R_min": 0.425,
      "Rmax_global": 20.045780284087446
    },
    "20.00": {
      "b": 20.0,
      "H_star": 0.1,
      "f_BM": 0.0846725554874244,
      "A_BM": 1.7816832237873415,
      "G_BM": 0.15085967162714686,
      "BM_count": 0,
      "R_min": 0.425,
      "Rmax_global": 20.045780284087446
    },
    "25.00": {
      "b": 25.0,
      "H_star": 0.1,
      "f_BM": 0.05216246878055162,
      "A_BM": 1.8465098425287683,
      "G_BM": 0.09631851201388816,
      "BM_count": 0,
      "R_min": 0.425,
      "Rmax_global": 20.045780284087446
    },
    "32.00": {
      "b": 32.0,
      "H_star": 0.1,
      "f_BM": 0.027050860893928583,
      "A_BM": 1.9137617952905626,
      "G_BM": 0.05176890410852004,
      "BM_count": 0,
      "R_min": 0.425,
      "Rmax_global": 20.045780284087446
    },
    "40.00": {
      "b": 40.0,
      "H_star": 0.1,
      "f_BM": 0.013041656197522256,
      "A_BM": 1.9701763881612138,
      "G_BM": 0.025694363102874707,
      "BM_count": 0,
      "R_min": 0.425,
      "Rmax_global": 20.045780284087446
    }
  },
  "0.20": {
    "1.00": {
      "b": 1.0,
      "H_star": 0.2,
      "f_BM": 0.4811272431544683,
      "A_BM": 1.3028044256949776,
      "G_BM": 0.626814701704065,
      "BM_count": 0,
      "R_min": 0.425,
      "Rmax_global": 20.045780284087446
    },
    "2.00": {
      "b": 2.0,
      "H_star": 0.2,
      "f_BM": 0.38374967436804247,
      "A_BM": 1.404520896937787,
      "G_BM": 0.5389844368429867,
      "BM_count": 0,
      "R_min": 0.425,
      "Rmax_global": 20.045780284087446
    },
    "3.00": {
      "b": 3.0,
      "H_star": 0.2,
      "f_BM": 0.3022432028234645,
      "A_BM": 1.4921478408842221,
      "G_BM": 0.4509915425149646,
      "BM_count": 0,
      "R_min": 0.425,
      "Rmax_global": 20.045780284087446
    },
    "4.00": {
      "b": 4.0,
      "H_star": 0.2,
      "f_BM": 0.23735441143130376,
      "A_BM": 1.5656147018078372,
      "G_BM": 0.3716055560757954,
      "BM_count": 0,
      "R_min": 0.425,
      "Rmax_global": 20.045780284087446
    },
    "5.00": {
      "b": 5.0,
      "H_star": 0.2,
      "f_BM": 0.18680279388536777,
      "A_BM": 1.6268957818565621,
      "G_BM": 0.30390867741112565,
      "BM_count": 0,
      "R_min": 0.425,
      "Rmax_global": 20.045780284087446
    },
    "6.00": {
      "b": 6.0,
      "H_star": 0.2,
      "f_BM": 0.1476572018998763,
      "A_BM": 1.6783333117185217,
      "G_BM": 0.2478180006637098,
      "BM_count": 0,
      "R_min": 0.425,
      "Rmax_global": 20.045780284087446
    },
    "8.00": {
      "b": 8.0,
      "H_star": 0.2,
      "f_BM": 0.09364475028293004,
      "A_BM": 1.759467647790072,
      "G_BM": 0.16476490850819558,
      "BM_count": 0,
      "R_min": 0.425,
      "Rmax_global": 20.045780284087446
    },
    "10.00": {
      "b": 10.0,
      "H_star": 0.2,
      "f_BM": 0.06049720379368719,
      "A_BM": 1.8206391861510003,
      "G_BM": 0.11014357987934986,
      "BM_count": 0,
      "R_min": 0.425,
      "Rmax_global": 20.045780284087446
    },
    "12.00": {
      "b": 12.0,
      "H_star": 0.2,
      "f_BM": 0.039687769310546975,
      "A_BM": 1.8686638653746417,
      "G_BM": 0.07416310040794379,
      "BM_count": 0,
      "R_min": 0.425,
      "Rmax_global": 20.045780284087446
    },
    "16.00": {
      "b": 16.0,
      "H_star": 0.2,
      "f_BM": 0.017692091373400772,
      "A_BM": 1.9399360398871803,
      "G_BM": 0.03432152567623724,
      "BM_count": 0,
      "R_min": 0.425,
      "Rmax_global": 20.045780284087446
    },
    "20.00": {
      "b": 20.0,
      "H_star": 0.2,
      "f_BM": 0.008161459734048304,
      "A_BM": 1.9909650883532213,
      "G_BM": 0.01624918140049074,
      "BM_count": 0,
      "R_min": 0.425,
      "Rmax_global": 20.045780284087446
    },
    "25.00": {
      "b": 25.0,
      "H_star": 0.2,
      "f_BM": 0.003208513443046574,
      "A_BM": 2.0380573700671754,
      "G_BM": 0.006539134469560678,
      "BM_count": 0,
      "R_min": 0.425,
      "Rmax_global": 20.045780284087446
    },
    "32.00": {
      "b": 32.0,
      "H_star": 0.2,
      "f_BM": 0.0009065652473207545,
      "A_BM": 2.0854807195195644,
      "G_BM": 0.001890624344273919,
      "BM_count": 0,
      "R_min": 0.425,
      "Rmax_global": 20.045780284087446
    },
    "40.00": {
      "b": 40.0,
      "H_star": 0.2,
      "f_BM": 0.00022297673088749663,
      "A_BM": 2.124132668161641,
      "G_BM": 0.0004736321583180184,
      "BM_count": 0,
      "R_min": 0.425,
      "Rmax_global": 20.045780284087446
    }
  },
  "0.50": {
    "1.00": {
      "b": 1.0,
      "H_star": 0.5,
      "f_BM": 0.1486706239813722,
      "A_BM": 1.7546747768520747,
      "G_BM": 0.260868593958973,
      "BM_count": 0,
      "R_min": 0.425,
      "Rmax_global": 20.045780284087446
    },
    "2.00": {
      "b": 2.0,
      "H_star": 0.5,
      "f_BM": 0.08903563927387113,
      "A_BM": 1.813557733834846,
      "G_BM": 0.16147127219205856,
      "BM_count": 0,
      "R_min": 0.425,
      "Rmax_global": 20.045780284087446
    },
    "3.00": {
      "b": 3.0,
      "H_star": 0.5,
      "f_BM": 0.05186121756334395,
      "A_BM": 1.8648538314279586,
      "G_BM": 0.0967135902755209,
      "BM_count": 0,
      "R_min": 0.425,
      "Rmax_global": 20.045780284087446
    },
    "4.00": {
      "b": 4.0,
      "H_star": 0.5,
      "f_BM": 0.030005831555228322,
      "A_BM": 1.9082694150680277,
      "G_BM": 0.05725921063052532,
      "BM_count": 0,
      "R_min": 0.425,
      "Rmax_global": 20.045780284087446
    },
    "5.00": {
      "b": 5.0,
      "H_star": 0.5,
      "f_BM": 0.017444456181202175,
      "A_BM": 1.9447074792056376,
      "G_BM": 0.033924364406258886,
      "BM_count": 0,
      "R_min": 0.425,
      "Rmax_global": 20.045780284087446
    },
    "6.00": {
      "b": 6.0,
      "H_star": 0.5,
      "f_BM": 0.01024327400020255,
      "A_BM": 1.975378100776072,
      "G_BM": 0.02023433914024903,
      "BM_count": 0,
      "R_min": 0.425,
      "Rmax_global": 20.045780284087446
    },
    "8.00": {
      "b": 8.0,
      "H_star": 0.5,
      "f_BM": 0.0036581477394451827,
      "A_BM": 2.0237255318279246,
      "G_BM": 0.007403086979513822,
      "BM_count": 0,
      "R_min": 0.425,
      "Rmax_global": 20.045780284087446
    },
    "10.00": {
      "b": 10.0,
      "H_star": 0.5,
      "f_BM": 0.0013656213789286938,
      "A_BM": 2.059978848507285,
      "G_BM": 0.002813151155662461,
      "BM_count": 0,
      "R_min": 0.425,
      "Rmax_global": 20.045780284087446
    },
    "12.00": {
      "b": 12.0,
      "H_star": 0.5,
      "f_BM": 0.0005292314347046259,
      "A_BM": 2.0882194755925587,
      "G_BM": 0.0011051513890459913,
      "BM_count": 0,
      "R_min": 0.425,
      "Rmax_global": 20.045780284087446
    },
    "16.00": {
      "b": 16.0,
      "H_star": 0.5,
      "f_BM": 8.668465935375193e-05,
      "A_BM": 2.129639515458883,
      "G_BM": 0.00018460707594384262,
      "BM_count": 0,
      "R_min": 0.425,
      "Rmax_global": 20.045780284087446
    },
    "20.00": {
      "b": 20.0,
      "H_star": 0.5,
      "f_BM": 1.5460138892888433e-05,
      "A_BM": 2.1588681924099697,
      "G_BM": 3.3376402106097124e-05,
      "BM_count": 0,
      "R_min": 0.425,
      "Rmax_global": 20.045780284087446
    },
    "25.00": {
      "b": 25.0,
      "H_star": 0.5,
      "f_BM": 1.9486931709134247e-06,
      "A_BM": 2.1854978953553585,
      "G_BM": 4.258864823724649e-06,
      "BM_count": 0,
      "R_min": 0.425,
      "Rmax_global": 20.045780284087446
    },
    "32.00": {
      "b": 32.0,
      "H_star": 0.5,
      "f_BM": 1.1958365010748154e-07,
      "A_BM": 2.211977260741268,
      "G_BM": 2.6451631479418927e-07,
      "BM_count": 0,
      "R_min": 0.425,
      "Rmax_global": 20.045780284087446
    },
    "40.00": {
      "b": 40.0,
      "H_star": 0.5,
      "f_BM": 5.474927109856785e-09,
      "A_BM": 2.2333163763655315,
      "G_BM": 1.2227244373850769e-08,
      "BM_count": 0,
      "R_min": 0.425,
      "Rmax_global": 20.045780284087446
    }
  },
  "1.00": {
    "1.00": {
      "b": 1.0,
      "H_star": 1.0,
      "f_BM": 0.014359907284755051,
      "A_BM": 2.068469385585937,
      "G_BM": 0.029703028598368302,
      "BM_count": 0,
      "R_min": 0.425,
      "Rmax_global": 20.045780284087446
    },
    "2.00": {
      "b": 2.0,
      "H_star": 1.0,
      "f_BM": 0.006011632426820944,
      "A_BM": 2.08819715321074,
      "G_BM": 0.01255347371983687,
      "BM_count": 0,
      "R_min": 0.425,
      "Rmax_global": 20.045780284087446
    },
    "3.00": {
      "b": 3.0,
      "H_star": 1.0,
      "f_BM": 0.0024081132007330447,
      "A_BM": 2.106545647874501,
      "G_BM": 0.005072800382593329,
      "BM_count": 0,
      "R_min": 0.425,
      "Rmax_global": 20.045780284087446
    },
    "4.00": {
      "b": 4.0,
      "H_star": 1.0,
      "f_BM": 0.0009555339757944518,
      "A_BM": 2.1229026366202537,
      "G_BM": 0.0020285055965942756,
      "BM_count": 0,
      "R_min": 0.425,
      "Rmax_global": 20.045780284087446
    },
    "5.00": {
      "b": 5.0,
      "H_star": 1.0,
      "f_BM": 0.000382941102839346,
      "A_BM": 2.137219890360374,
      "G_BM": 0.0008184293418247877,
      "BM_count": 0,
      "R_min": 0.425,
      "Rmax_global": 20.045780284087446
    },
    "6.00": {
      "b": 6.0,
      "H_star": 1.0,
      "f_BM": 0.0001564095828523189,
      "A_BM": 2.1496872541471492,
      "G_BM": 0.00033623168668410247,
      "BM_count": 0,
      "R_min": 0.425,
      "Rmax_global": 20.045780284087446
    },
    "8.00": {
      "b": 8.0,
      "H_star": 1.0,
      "f_BM": 2.789883516329256e-05,
      "A_BM": 2.1700963359354715,
      "G_BM": 6.0543159964728874e-05,
      "BM_count": 0,
      "R_min": 0.425,
      "Rmax_global": 20.045780284087446
    },
    "10.00": {
      "b": 10.0,
      "H_star": 1.0,
      "f_BM": 5.4207222262928375e-06,
      "A_BM": 2.1859828931937106,
      "G_BM": 1.1849606055431068e-05,
      "BM_count": 0,
      "R_min": 0.425,
      "Rmax_global": 20.045780284087446
    },
    "12.00": {
      "b": 12.0,
      "H_star": 1.0,
      "f_BM": 1.1334987955138769e-06,
      "A_BM": 2.1986858441062327,
      "G_BM": 2.4922077560078264e-06,
      "BM_count": 0,
      "R_min": 0.425,
      "Rmax_global": 20.045780284087446
    },
    "16.00": {
      "b": 16.0,
      "H_star": 1.0,
      "f_BM": 5.89317602552493e-08,
      "A_BM": 2.217809720714105,
      "G_BM": 1.3069943075288505e-07,
      "BM_count": 0,
      "R_min": 0.425,
      "Rmax_global": 20.045780284087446
    },
    "20.00": {
      "b": 20.0,
      "H_star": 1.0,
      "f_BM": 3.6414117853325363e-09,
      "A_BM": 2.2316504934290244,
      "G_BM": 8.126358407515619e-09,
      "BM_count": 0,
      "R_min": 0.425,
      "Rmax_global": 20.045780284087446
    },
    "25.00": {
      "b": 25.0,
      "H_star": 1.0,
      "f_BM": 1.3333537383578196e-10,
      "A_BM": 2.24452082524867,
      "G_BM": 2.9927402331672926e-10,
      "BM_count": 0,
      "R_min": 0.425,
      "Rmax_global": 20.045780284087446
    },
    "32.00": {
      "b": 32.0,
      "H_star": 1.0,
      "f_BM": 1.6311770266286405e-12,
      "A_BM": 2.2576002256577326,
      "G_BM": 3.682545623404528e-12,
      "BM_count": 0,
      "R_min": 0.425,
      "Rmax_global": 20.045780284087446
    },
    "40.00": {
      "b": 40.0,
      "H_star": 1.0,
      "f_BM": 1.3299023867690706e-14,
      "A_BM": 2.268397396313068,
      "G_BM": 3.0167471114974944e-14,
      "BM_count": 0,
      "R_min": 0.425,
      "Rmax_global": 20.045780284087446
    }
  },
  "1.50": {
    "1.00": {
      "b": 1.0,
      "H_star": 1.5,
      "f_BM": 0.00046076324464994255,
      "A_BM": 2.231823454389733,
      "G_BM": 0.0010283422163304564,
      "BM_count": 0,
      "R_min": 0.425,
      "Rmax_global": 20.045780284087446
    },
    "2.00": {
      "b": 2.0,
      "H_star": 1.5,
      "f_BM": 0.00014463025837976835,
      "A_BM": 2.2400066687928093,
      "G_BM": 0.00032397274327990817,
      "BM_count": 0,
      "R_min": 0.425,
      "Rmax_global": 20.045780284087446
    },
    "3.00": {
      "b": 3.0,
      "H_star": 1.5,
      "f_BM": 4.238670927482773e-05,
      "A_BM": 2.2485193712539413,
      "G_BM": 9.530733688815926e-05,
      "BM_count": 0,
      "R_min": 0.425,
      "Rmax_global": 20.045780284087446
    },
    "4.00": {
      "b": 4.0,
      "H_star": 1.5,
      "f_BM": 1.217226889096108e-05,
      "A_BM": 2.2567895010061574,
      "G_BM": 2.747024863654483e-05,
      "BM_count": 0,
      "R_min": 0.425,
      "Rmax_global": 20.045780284087446
    },
    "5.00": {
      "b": 5.0,
      "H_star": 1.5,
      "f_BM": 3.5197062746561075e-06,
      "A_BM": 2.264603340229741,
      "G_BM": 7.970738586213799e-06,
      "BM_count": 0,
      "R_min": 0.425,
      "Rmax_global": 20.045780284087446
    },
    "6.00": {
      "b": 6.0,
      "H_star": 1.5,
      "f_BM": 1.0380930425887555e-06,
      "A_BM": 2.2719183235551283,
      "G_BM": 2.358462605012488e-06,
      "BM_count": 0,
      "R_min": 0.425,
      "Rmax_global": 20.045780284087446
    },
    "8.00": {
      "b": 8.0,
      "H_star": 1.5,
      "f_BM": 9.721292310472288e-08,
      "A_BM": 2.285230168121068,
      "G_BM": 2.221539046101463e-07,
      "BM_count": 0,
      "R_min": 0.425,
      "Rmax_global": 20.045780284087446
    },
    "10.00": {
      "b": 10.0,
      "H_star": 1.5,
      "f_BM": 9.960873056602507e-09,
      "A_BM": 2.297269786711425,
      "G_BM": 2.2882812722200818e-08,
      "BM_count": 0,
      "R_min": 0.425,
      "Rmax_global": 20.045780284087446
    },
    "12.00": {
      "b": 12.0,
      "H_star": 1.5,
      "f_BM": 1.0857017792545382e-09,
      "A_BM": 2.3085502233529196,
      "G_BM": 2.5063970849927263e-09,
      "BM_count": 0,
      "R_min": 0.425,
      "Rmax_global": 20.045780284087446
    },
    "16.00": {
      "b": 16.0,
      "H_star": 1.5,
      "f_BM": 1.2871554630570239e-11,
      "A_BM": 2.329459659836796,
      "G_BM": 2.9983767271298884e-11,
      "BM_count": 0,
      "R_min": 0.425,
      "Rmax_global": 20.045780284087446
    },
    "20.00": {
      "b": 20.0,
      "H_star": 1.5,
      "f_BM": 7.401572306305262e-14,
      "A_BM": 2.344577459630684,
      "G_BM": 1.7353559595190013e-13,
      "BM_count": 0,
      "R_min": 0.425,
      "Rmax_global": 20.045780284087446
    },
    "25.00": {
      "b": 25.0,
      "H_star": 1.5,
      "f_BM": 0.0,
      "A_BM": 0.0,
      "G_BM": 0.0,
      "BM_count": 0,
      "R_min": 0.425,
      "Rmax_global": 20.045780284087446
    },
    "32.00": {
      "b": 32.0,
      "H_star": 1.5,
      "f_BM": 0.0,
      "A_BM": 0.0,
      "G_BM": 0.0,
      "BM_count": 0,
      "R_min": 0.425,
      "Rmax_global": 20.045780284087446
    },
    "40.00": {
      "b": 40.0,
      "H_star": 1.5,
      "f_BM": 0.0,
      "A_BM": 0.0,
      "G_BM": 0.0,
      "BM_count": 0,
      "R_min": 0.425,
      "Rmax_global": 20.045780284087446
    }
  },
  "2.00": {
    "1.00": {
      "b": 1.0,
      "H_star": 2.0,
      "f_BM": 2.562481803951145e-07,
      "A_BM": 2.3285100914583845,
      "G_BM": 5.966764739678727e-07,
      "BM_count": 0,
      "R_min": 0.425,
      "Rmax_global": 20.045780284087446
    },
    "2.00": {
      "b": 2.0,
      "H_star": 2.0,
      "f_BM": 2.5212184507541374e-08,
      "A_BM": 2.3361271915045037,
      "G_BM": 5.889886978529599e-08,
      "BM_count": 0,
      "R_min": 0.425,
      "Rmax_global": 20.045780284087446
    },
    "3.00": {
      "b": 3.0,
      "H_star": 2.0,
      "f_BM": 1.0644930291415195e-09,
      "A_BM": 2.343548673837569,
      "G_BM": 2.4946912267539444e-09,
      "BM_count": 0,
      "R_min": 0.425,
      "Rmax_global": 20.045780284087446
    },
    "4.00": {
      "b": 4.0,
      "H_star": 2.0,
      "f_BM": 0.0,
      "A_BM": 0.0,
      "G_BM": 0.0,
      "BM_count": 0,
      "R_min": 0.425,
      "Rmax_global": 20.045780284087446
    },
    "5.00": {
      "b": 5.0,
      "H_star": 2.0,
      "f_BM": 0.0,
      "A_BM": 0.0,
      "G_BM": 0.0,
      "BM_count": 0,
      "R_min": 0.425,
      "Rmax_global": 20.045780284087446
    },
    "6.00": {
      "b": 6.0,
      "H_star": 2.0,
      "f_BM": 0.0,
      "A_BM": 0.0,
      "G_BM": 0.0,
      "BM_count": 0,
      "R_min": 0.425,
      "Rmax_global": 20.045780284087446
    },
    "8.00": {
      "b": 8.0,
      "H_star": 2.0,
      "f_BM": 0.0,
      "A_BM": 0.0,
      "G_BM": 0.0,
      "BM_count": 0,
      "R_min": 0.425,
      "Rmax_global": 20.045780284087446
    },
    "10.00": {
      "b": 10.0,
      "H_star": 2.0,
      "f_BM": 0.0,
      "A_BM": 0.0,
      "G_BM": 0.0,
      "BM_count": 0,
      "R_min": 0.425,
      "Rmax_global": 20.045780284087446
    },
    "12.00": {
      "b": 12.0,
      "H_star": 2.0,
      "f_BM": 0.0,
      "A_BM": 0.0,
      "G_BM": 0.0,
      "BM_count": 0,
      "R_min": 0.425,
      "Rmax_global": 20.045780284087446
    },
    "16.00": {
      "b": 16.0,
      "H_star": 2.0,
      "f_BM": 0.0,
      "A_BM": 0.0,
      "G_BM": 0.0,
      "BM_count": 0,
      "R_min": 0.425,
      "Rmax_global": 20.045780284087446
    },
    "20.00": {
      "b": 20.0,
      "H_star": 2.0,
      "f_BM": 0.0,
      "A_BM": 0.0,
      "G_BM": 0.0,
      "BM_count": 0,
      "R_min": 0.425,
      "Rmax_global": 20.045780284087446
    },
    "25.00": {
      "b": 25.0,
      "H_star": 2.0,
      "f_BM": 0.0,
      "A_BM": 0.0,
      "G_BM": 0.0,
      "BM_count": 0,
      "R_min": 0.425,
      "Rmax_global": 20.045780284087446
    },
    "32.00": {
      "b": 32.0,
      "H_star": 2.0,
      "f_BM": 0.0,
      "A_BM": 0.0,
      "G_BM": 0.0,
      "BM_count": 0,
      "R_min": 0.425,
      "Rmax_global": 20.045780284087446
    },
    "40.00": {
      "b": 40.0,
      "H_star": 2.0,
      "f_BM": 0.0,
      "A_BM": 0.0,
      "G_BM": 0.0,
      "BM_count": 0,
      "R_min": 0.425,
      "Rmax_global": 20.045780284087446
    }
  }
}